nso_client/__init__.py
nso_client/exceptions.py
nso_client/py.typed
nso_client/types.py
python_nso_client-0.1.2.dist-info/METADATA
python_nso_client-0.1.2.dist-info/WHEEL
python_nso_client-0.1.2.dist-info/licenses/LICENSE.txt
python_nso_client-0.1.2.dist-info/RECORD
