Metadata-Version: 2.4
Name: python-nso-client
Version: 0.1.2
Summary: Add your description here
Author-email: James Harr <jharr@internet2.edu>
License-Expression: Apache-2.0
License-File: LICENSE.txt
Requires-Python: >=3.11
Requires-Dist: httpx>=0.28.1
Requires-Dist: structlog>=24.0.0
